articlemeta/__init__.py
articlemeta/client.py
articlemeta/thrift/__init__.py
articlemeta/thrift/articlemeta.thrift
articlemetaapi-1.26.2.dist-info/METADATA
articlemetaapi-1.26.2.dist-info/RECORD
articlemetaapi-1.26.2.dist-info/WHEEL
articlemetaapi-1.26.2.dist-info/top_level.txt
tests/__init__.py
tests/test_client.py
