Metadata-Version: 2.1
Name: articlemetaapi
Version: 1.26.2
Summary: Library that implements the endpoints of the ArticleMeta API
Home-page: http://github.com/scieloorg/processing
Author: SciELO
Author-email: scielo-dev@googlegroups.com
Maintainer: Fabio Batalha
Maintainer-email: fabio.batalha@scielo.org
License: UNKNOWN
Platform: UNKNOWN
Classifier: Development Status :: 4 - Beta
Classifier: Intended Audience :: Developers
Classifier: Programming Language :: Python :: 3
Requires-Dist: thriftpy (==0.3.9)
Requires-Dist: requests (>=2.19.1)
Requires-Dist: xylose (>=1.33.1)
